sync_pre_commit_lock-0.8.0.dist-info/METADATA
sync_pre_commit_lock-0.8.0.dist-info/WHEEL
sync_pre_commit_lock-0.8.0.dist-info/entry_points.txt
sync_pre_commit_lock-0.8.0.dist-info/licenses/LICENSE
sync_pre_commit_lock/__init__.py
sync_pre_commit_lock/_compat.py
sync_pre_commit_lock/_version.py
sync_pre_commit_lock/actions/__init__.py
sync_pre_commit_lock/actions/install_hooks.py
sync_pre_commit_lock/actions/sync_hooks.py
sync_pre_commit_lock/config.py
sync_pre_commit_lock/db.py
sync_pre_commit_lock/pdm_plugin.py
sync_pre_commit_lock/poetry_plugin.py
sync_pre_commit_lock/pre_commit_config.py
sync_pre_commit_lock/py.typed
sync_pre_commit_lock/shell.py
sync_pre_commit_lock/utils.py
sync_pre_commit_lock/uv.py
sync_pre_commit_lock-0.8.0.dist-info/RECORD
