Metadata-Version: 2.1
Name: sync-pre-commit-lock
Version: 0.8.0
Summary: PDM plugin to sync your pre-commit versions with your lockfile, and install them, all automatically.
Author-Email: Gabriel Dugny <sync-pre-commit-lock@dugny.me>
License:                     GNU GENERAL PUBLIC LICENSE
Classifier: Development Status :: 4 - Beta
Classifier: Environment :: Console
Classifier: Environment :: Plugins
Classifier: Intended Audience :: Developers
Classifier: License :: OSI Approved :: GNU General Public License v3 (GPLv3)
Classifier: Operating System :: OS Independent
Classifier: Programming Language :: Python
Classifier: Programming Language :: Python :: 3 :: Only
Classifier: Programming Language :: Python :: 3.9
Classifier: Programming Language :: Python :: 3.10
Classifier: Programming Language :: Python :: 3.11
Classifier: Programming Language :: Python :: 3.12
Classifier: Programming Language :: Python :: 3.13
Classifier: Programming Language :: Python :: 3.14
Classifier: Typing :: Typed
Project-URL: Bug Tracker, https://github.com/GabDug/sync-pre-commit-lock/issues
Project-URL: Changelog, https://github.com/GabDug/sync-pre-commit-lock/releases
Project-URL: Homepage, https://github.com/GabDug/sync-pre-commit-lock
Requires-Python: >=3.9
Requires-Dist: packaging>=24.1
Requires-Dist: strictyaml>=1.7.3
Requires-Dist: tomli>=2; python_version < "3.11"
Requires-Dist: typing-extensions; python_version < "3.10"
Provides-Extra: pdm
Requires-Dist: pdm>=2.7.4; extra == "pdm"
Provides-Extra: poetry
Requires-Dist: poetry>=1.6; extra == "poetry"
